kerneloose/__init__.py
kerneloose/kerneloose.py
kerneloose-0.0.2.dist-info/LICENSE
kerneloose-0.0.2.dist-info/METADATA
kerneloose-0.0.2.dist-info/WHEEL
kerneloose-0.0.2.dist-info/top_level.txt
kerneloose-0.0.2.dist-info/RECORD
