Metadata-Version: 2.1
Name: kerneloose
Version: 0.0.2
Summary: Kernel method for out-of-sample extension
Home-page: https://github.com/einbandi/kerneloose
Author: Andreas Hinterreiter
Author-email: andreas.hinterreiter@jku.at
License: UNKNOWN
Platform: UNKNOWN
Classifier: Programming Language :: Python :: 3
Classifier: License :: OSI Approved :: MIT License
Classifier: Operating System :: OS Independent
